Workbook
Name NativeTimeline_Transaction_Date: #N/A

Sheet RACI_Chart
A1: Dataset / Process | B1: Finance Analyst | C1: Project Manager | D1: Department Head | E1: Data Engineer | F1: BI Analyst | G1: Procurement Officer
A2: Capex_Budget | B2: R/A | C2: C | D2: C | E2: I | F2: I | G2: I
A3: Capex_Actuals | B3: A/R | C3: C | D3: I | E3: R | F3: I | G3: C
A4: Capex_Forecast | B4: R/A | C4: C | D4: C | E4: I | F4: I | G4: I
A5: Projects_Master | B5: C | C5: R/A | D5: I | E5: C | F5: I | G5: I
A6: Vendors | B6: I | C6: I | D6: I | E6: C | F6: I | G6: A/R
A7: Departments | B7: C | C7: I | D7: A/R | E7: I | F7: I | G7: I
A8: Budget vs Actual Reporting | B8: A/R | C8: C | D8: C | E8: I | F8: I | G8: I
A9: Forecast Variance Analysis | B9: A/R | C9: C | D9: C | E9: I | F9: I | G9: I
A10: Data Integration / ETL | B10: I | C10: I | D10: I | E10: A/R | F10: I | G10: I
A11: Dashboard Development (Power BI / Excel) | B11: A/R | C11: C | D11: I | E11: C | F11: I | G11: I
A19: R = Responsible (does the work)
A20: A = Accountable (owns the outcome)
A21: C = Consulted (provides input)
A22: I = Informed (kept up to date)

Sheet Variance_Analysis
A1: Project_ID | B1: Project_Name | C1: Month | D1: Approved_Budget | E1: Actual Spend | F1: Variance | G1: Variance%
A2: PRJ0001 | B2: Infra - PRJ0001 | C2: 45139 | D2: 5543627 | E2: =SUMIF(Capex_Actuals!B:B,Variance_Analysis!A2,Capex_Actuals!E:E) -> 4840905 | F2: =D2-E2 -> 702722 | G2: =F2/D2 -> 0.12676214
A3: PRJ0002 | B3: Infra - PRJ0002 | C3: 45372 | D3: 6018833 | E3: =SUMIF(Capex_Actuals!B:B,Variance_Analysis!A3,Capex_Actuals!E:E) -> 5053310 | F3: =D3-E3 -> 965523 | G3: =F3/D3 -> 0.16041698
A4: PRJ0003 | B4: R&D - PRJ0003 | C4: 45190 | D4: 6171576 | E4: =SUMIF(Capex_Actuals!B:B,Variance_Analysis!A4,Capex_Actuals!E:E) -> 7051753 | F4: =D4-E4 -> -880177 | G4: =F4/D4 -> -0.14261787
A5: PRJ0004 | B5: R&D - PRJ0004 | C5: 45232 | D5: 444469 | E5: =SUMIF(Capex_Actuals!B:B,Variance_Analysis!A5,Capex_Actuals!E:E) -> 526108 | F5: =D5-E5 -> -81639 | G5: =F5/D5 -> -0.1836776
A6: PRJ0005 | B6: Infra - PRJ0005 | C6: 45192 | D6: 8956949 | E6: =SUMIF(Capex_Actuals!B:B,Variance_Analysis!A6,Capex_Actuals!E:E) -> 9029209 | F6: =D6-E6 -> -72260 | G6: =F6/D6 -> -0.0080674792
A7: PRJ0006 | B7: Platform - PRJ0006 | C7: 45139 | D7: 3812561 | E7: =SUMIF(Capex_Actuals!B:B,Variance_Analysis!A7,Capex_Actuals!E:E) -> 4536117 | F7: =D7-E7 -> -723556 | G7: =F7/D7 -> -0.18978214
A8: PRJ0007 | B8: Platform - PRJ0007 | C8: 45236 | D8: 3308526 | E8: =SUMIF(Capex_Actuals!B:B,Variance_Analysis!A8,Capex_Actuals!E:E) -> 2983438 | F8: =D8-E8 -> 325088 | G8: =F8/D8 -> 0.098257653
A9: PRJ0008 | B9: Platform - PRJ0008 | C9: 45139 | D9: 8079602 | E9: =SUMIF(Capex_Actuals!B:B,Variance_Analysis!A9,Capex_Actuals!E:E) -> 8818141 | F9: =D9-E9 -> -738539 | G9: =F9/D9 -> -0.091407844
A10: PRJ0009 | B10: R&D - PRJ0009 | C10: 45462 | D10: 7006978 | E10: =SUMIF(Capex_Actuals!B:B,Variance_Analysis!A10,Capex_Actuals!E:E) -> 7061476 | F10: =D10-E10 -> -54498 | G10: =F10/D10 -> -0.0077776753
A11: PRJ0010 | B11: Platform - PRJ0010 | C11: 45355 | D11: 7629267 | E11: =SUMIF(Capex_Actuals!B:B,Variance_Analysis!A11,Capex_Actuals!E:E) -> 8164037 | F11: =D11-E11 -> -534770 | G11: =F11/D11 -> -0.070094545
A12: PRJ0011 | B12: Hybrid Clients - PRJ0011 | C12: 45139 | D12: 2712927 | E12: =SUMIF(Capex_Actuals!B:B,Variance_Analysis!A12,Capex_Actuals!E:E) -> 3478205 | F12: =D12-E12 -> -765278 | G12: =F12/D12 -> -0.28208573
A13: PRJ0012 | B13: Platform - PRJ0012 | C13: 45274 | D13: 5466843 | E13: =SUMIF(Capex_Actuals!B:B,Variance_Analysis!A13,Capex_Actuals!E:E) -> 5899923 | F13: =D13-E13 -> -433080 | G13: =F13/D13 -> -0.079219396
... A46: PRJ0045 | B46: Hybrid Clients - PRJ0045 | C46: 45185 | D46: 501071 | E46: =SUMIF(Capex_Actuals!B:B,Variance_Analysis!A46,Capex_Actuals!E:E) -> 560878 | F46: =D46-E46 -> -59807 | G46: =F46/D46 -> -0.11935833

Sheet Vendor_Analysis
A1: Transaction_ID | B1: Project_ID | C1: Vendor | D1: Transaction_Date | E1: Amount_Spent | F1: Payment_Term(DAYS) | G1: Payment_Term(DAYS) | H1: Payment_Due_Date
A2: TX0001-001 | B2: PRJ0001 | C2: VEND0017 | D2: 45179 | E2: 38577 | F2: =INDEX(Vendors!E:E,MATCH(Vendor_Analysis!C2,Vendors!A:A,0)) -> 45 | G2: 45 | H2: =F2+D2 -> 45224
A3: TX0001-002 | B3: PRJ0001 | C3: VEND0024 | D3: 45181 | E3: 79555 | F3: =INDEX(Vendors!E:E,MATCH(Vendor_Analysis!C3,Vendors!A:A,0)) -> 30 | G3: 30 | H3: =D3+F3 -> 45211
A4: TX0001-003 | B4: PRJ0001 | C4: VEND0006 | D4: 45184 | E4: 73361 | F4: =INDEX(Vendors!E:E,MATCH(Vendor_Analysis!C4,Vendors!A:A,0)) -> 90 | G4: 90 | H4: =D4+F4 -> 45274
A5: TX0001-004 | B5: PRJ0001 | C5: VEND0016 | D5: 45191 | E5: 55178 | F5: =INDEX(Vendors!E:E,MATCH(Vendor_Analysis!C5,Vendors!A:A,0)) -> 60 | G5: 60 | H5: =D5+F5 -> 45251
A6: TX0001-005 | B6: PRJ0001 | C6: VEND0009 | D6: 45197 | E6: 97145 | F6: =INDEX(Vendors!E:E,MATCH(Vendor_Analysis!C6,Vendors!A:A,0)) -> 30 | G6: 30 | H6: =D6+F6 -> 45227
A7: TX0001-006 | B7: PRJ0001 | C7: VEND0006 | D7: 45201 | E7: 97663 | F7: =INDEX(Vendors!E:E,MATCH(Vendor_Analysis!C7,Vendors!A:A,0)) -> 90 | G7: 90 | H7: =D7+F7 -> 45291
A8: TX0001-007 | B8: PRJ0001 | C8: VEND0015 | D8: 45208 | E8: 50793 | F8: =INDEX(Vendors!E:E,MATCH(Vendor_Analysis!C8,Vendors!A:A,0)) -> 90 | G8: 90 | H8: =D8+F8 -> 45298
A9: TX0001-008 | B9: PRJ0001 | C9: VEND0012 | D9: 45209 | E9: 84554 | F9: =INDEX(Vendors!E:E,MATCH(Vendor_Analysis!C9,Vendors!A:A,0)) -> 90 | G9: 90 | H9: =D9+F9 -> 45299
A10: TX0001-009 | B10: PRJ0001 | C10: VEND0025 | D10: 45213 | E10: 60509 | F10: =INDEX(Vendors!E:E,MATCH(Vendor_Analysis!C10,Vendors!A:A,0)) -> 60 | G10: 60 | H10: =D10+F10 -> 45273
A11: TX0001-010 | B11: PRJ0001 | C11: VEND0020 | D11: 45222 | E11: 82632 | F11: =INDEX(Vendors!E:E,MATCH(Vendor_Analysis!C11,Vendors!A:A,0)) -> 60 | G11: 60 | H11: =D11+F11 -> 45282
A12: TX0001-011 | B12: PRJ0001 | C12: VEND0009 | D12: 45241 | E12: 73839 | F12: =INDEX(Vendors!E:E,MATCH(Vendor_Analysis!C12,Vendors!A:A,0)) -> 30 | G12: 30 | H12: =D12+F12 -> 45271
A13: TX0001-012 | B13: PRJ0001 | C13: VEND0010 | D13: 45245 | E13: 161273 | F13: =INDEX(Vendors!E:E,MATCH(Vendor_Analysis!C13,Vendors!A:A,0)) -> 45 | G13: 45 | H13: =D13+F13 -> 45290
A14: TX0001-013 | B14: PRJ0001 | C14: VEND0021 | D14: 45248 | E14: 94389 | F14: =INDEX(Vendors!E:E,MATCH(Vendor_Analysis!C14,Vendors!A:A,0)) -> 60 | G14: 60 | H14: =D14+F14 -> 45308
... A1935: TX0045-050 | B1935: PRJ0045 | C1935: VEND0008 | D1935: 45760 | E1935: 8961 | F1935: =INDEX(Vendors!E:E,MATCH(Vendor_Analysis!C1935,Vendors!A:A,0)) -> 45 | G1935: 45 | H1935: =D1935+F1935 -> 45805

Sheet Scenario_Modelling
A1: Identifiers | E1: Budget_Data | G1: Actual_Data | J1: Scenario_Inputs | O1: Vendor_Input | Q1: Cashflow_Output | S1: Variance_Analysis
A2: Project_ID | B2: Project_Name | C2: Capex_Category | D2: DPT | E2: ApprovedBudget | F2: Budget_month | G2: Actual_Spend | H2: Remaining_Budget | I2: Actual_Spend_Month | J2: Scenario_Adjustment(%) | K2: Scenario_Delay(Months) | L2: Scenario_Remaining_Budget | M2: Scenario_Budget | N2: Scenario_Spend_Month | O2: Payment_Terms(Days) | P2: Payment_Due_Date | Q2: Scenario_Cashflow_Month | R2: Scenario_Cashflow_Amount | S2: Budget_vs_Actual | T2: Variance % | U2: Scenario_vs_budget | V2: Variance % | W2: Scenario_vs_actual | X2: Variance %
A3: PRJ0001 | B3: =Capex_Budgets!B2 -> Infra - PRJ0001 | C3: =Capex_Budgets!G2 -> Storage | D3: =Capex_Budgets!C2 -> DPT001 | E3: =Capex_Budgets!D2 -> 5543627 | F3: =INDEX(Capex_Budgets!E:E,MATCH(Scenario_Modelling!A3,Capex_Budgets!A:A)) -> 45139 | G3: =SUMIF(Capex_Actuals!B:B,Scenario_Modelling!A3,Capex_Actuals!E:E) -> 4840905 | H3: =E3-G3 -> 702722 | I3: {=MIN(IF(Capex_Actuals!B:B=Scenario_Modelling!A3,Capex_Actuals!D:D))} -> 45179 | J3: -0.5 | K3: 2 | L3: =IF(H3>=0, H3*(1+J3), H3*(1-J3)) -> 351361 | M3: =G3+L3 -> 5192266 | N3: =EDATE(I3,K3) -> 45240 | O3: =AVERAGEIFS(Vendor_Analysis!G:G,Vendor_Analysis!B:B,Scenario_Modelling!A3) -> 55.75 | P3: =N3+O3 -> 45295.75 | Q3: =P3 -> 45295.75 | R3: =L3 -> 351361 | S3: =E3-G3 -> 702722 | T3: =S3/E3 -> 0.12676214 | U3: =M3-E3 -> -351361 | V3: =U3/E3 -> -0.063381068 | W3: =M3-G3 -> 351361 | X3: =W3/G3 -> 0.072581676
A4: PRJ0002 | B4: =Capex_Budgets!B3 -> Infra - PRJ0002 | C4: =Capex_Budgets!G3 -> ProprietaryHardware | D4: =Capex_Budgets!C3 -> DPT004 | E4: =Capex_Budgets!D3 -> 6018833 | F4: =INDEX(Capex_Budgets!E:E,MATCH(Scenario_Modelling!A4,Capex_Budgets!A:A)) -> 45372 | G4: =SUMIF(Capex_Actuals!B:B,Scenario_Modelling!A4,Capex_Actuals!E:E) -> 5053310 | H4: =E4-G4 -> 965523 | I4: {=MIN(IF(Capex_Actuals!B:B=Scenario_Modelling!A4,Capex_Actuals!D:D))} -> 45379 | J4: 0.25 | K4: 2 | L4: =IF(H4>=0, H4*(1+J4), H4*(1-J4)) -> 1206903.8 | M4: =G4+L4 -> 6260213.8 | N4: =EDATE(I4,K4) -> 45440 | O4: =AVERAGEIFS(Vendor_Analysis!G:G,Vendor_Analysis!B:B,Scenario_Modelling!A4) -> 51 | P4: =N4+O4 -> 45491 | Q4: =P4 -> 45491 | R4: =L4 -> 1206903.8 | S4: =E4-G4 -> 965523 | T4: =S4/E4 -> 0.16041698 | U4: =M4-E4 -> 241380.75 | V4: =U4/E4 -> 0.040104244 | W4: =M4-G4 -> 1206903.8 | X4: =W4/G4 -> 0.2388343
A5: PRJ0003 | B5: =Capex_Budgets!B4 -> R&D - PRJ0003 | C5: =Capex_Budgets!G4 -> Compute | D5: =Capex_Budgets!C4 -> DPT001 | E5: =Capex_Budgets!D4 -> 6171576 | F5: =INDEX(Capex_Budgets!E:E,MATCH(Scenario_Modelling!A5,Capex_Budgets!A:A)) -> 45190 | G5: =SUMIF(Capex_Actuals!B:B,Scenario_Modelling!A5,Capex_Actuals!E:E) -> 7051753 | H5: =E5-G5 -> -880177 | I5: {=MIN(IF(Capex_Actuals!B:B=Scenario_Modelling!A5,Capex_Actuals!D:D))} -> 45190 | J5: 0.25 | K5: 2 | L5: =IF(H5>=0, H5*(1+J5), H5*(1-J5)) -> -660132.75 | M5: =G5+L5 -> 6391620.2 | N5: =EDATE(I5,K5) -> 45251 | O5: =AVERAGEIFS(Vendor_Analysis!G:G,Vendor_Analysis!B:B,Scenario_Modelling!A5) -> 60 | P5: =N5+O5 -> 45311 | Q5: =P5 -> 45311 | R5: =L5 -> -660132.75 | S5: =E5-G5 -> -880177 | T5: =S5/E5 -> -0.14261787 | U5: =M5-E5 -> 220044.25 | V5: =U5/E5 -> 0.035654467 | W5: =M5-G5 -> -660132.75 | X5: =W5/G5 -> -0.093612574
A6: PRJ0004 | B6: =Capex_Budgets!B5 -> R&D - PRJ0004 | C6: =Capex_Budgets!G5 -> DataCenter | D6: =Capex_Budgets!C5 -> DPT003 | E6: =Capex_Budgets!D5 -> 444469 | F6: =INDEX(Capex_Budgets!E:E,MATCH(Scenario_Modelling!A6,Capex_Budgets!A:A)) -> 45232 | G6: =SUMIF(Capex_Actuals!B:B,Scenario_Modelling!A6,Capex_Actuals!E:E) -> 526108 | H6: =E6-G6 -> -81639 | I6: {=MIN(IF(Capex_Actuals!B:B=Scenario_Modelling!A6,Capex_Actuals!D:D))} -> 45237 | J6: 0.25 | K6: 2 | L6: =IF(H6>=0, H6*(1+J6), H6*(1-J6)) -> -61229.25 | M6: =G6+L6 -> 464878.75 | N6: =EDATE(I6,K6) -> 45298 | O6: =AVERAGEIFS(Vendor_Analysis!G:G,Vendor_Analysis!B:B,Scenario_Modelling!A6) -> 54.807692 | P6: =N6+O6 -> 45352.808 | Q6: =P6 -> 45352.808 | R6: =L6 -> -61229.25 | S6: =E6-G6 -> -81639 | T6: =S6/E6 -> -0.1836776 | U6: =M6-E6 -> 20409.75 | V6: =U6/E6 -> 0.0459194 | W6: =M6-G6 -> -61229.25 | X6: =W6/G6 -> -0.11638152
A7: PRJ0005 | B7: =Capex_Budgets!B6 -> Infra - PRJ0005 | C7: =Capex_Budgets!G6 -> ProprietaryHardware | D7: =Capex_Budgets!C6 -> DPT001 | E7: =Capex_Budgets!D6 -> 8956949 | F7: =INDEX(Capex_Budgets!E:E,MATCH(Scenario_Modelling!A7,Capex_Budgets!A:A)) -> 45192 | G7: =SUMIF(Capex_Actuals!B:B,Scenario_Modelling!A7,Capex_Actuals!E:E) -> 9029209 | H7: =E7-G7 -> -72260 | I7: {=MIN(IF(Capex_Actuals!B:B=Scenario_Modelling!A7,Capex_Actuals!D:D))} -> 45212 | J7: 0.25 | K7: 2 | L7: =IF(H7>=0, H7*(1+J7), H7*(1-J7)) -> -54195 | M7: =G7+L7 -> 8975014 | N7: =EDATE(I7,K7) -> 45273 | O7: =AVERAGEIFS(Vendor_Analysis!G:G,Vendor_Analysis!B:B,Scenario_Modelling!A7) -> 52 | P7: =N7+O7 -> 45325 | Q7: =P7 -> 45325 | R7: =L7 -> -54195 | S7: =E7-G7 -> -72260 | T7: =S7/E7 -> -0.0080674792 | U7: =M7-E7 -> 18065 | V7: =U7/E7 -> 0.0020168698 | W7: =M7-G7 -> -54195 | X7: =W7/G7 -> -0.0060021869
A8: PRJ0006 | B8: =Capex_Budgets!B7 -> Platform - PRJ0006 | C8: =Capex_Budgets!G7 -> ProprietaryHardware | D8: =Capex_Budgets!C7 -> DPT002 | E8: =Capex_Budgets!D7 -> 3812561 | F8: =INDEX(Capex_Budgets!E:E,MATCH(Scenario_Modelling!A8,Capex_Budgets!A:A)) -> 45139 | G8: =SUMIF(Capex_Actuals!B:B,Scenario_Modelling!A8,Capex_Actuals!E:E) -> 4536117 | H8: =E8-G8 -> -723556 | I8: {=MIN(IF(Capex_Actuals!B:B=Scenario_Modelling!A8,Capex_Actuals!D:D))} -> 45141 | J8: 0.25 | K8: 2 | L8: =IF(H8>=0, H8*(1+J8), H8*(1-J8)) -> -542667 | M8: =G8+L8 -> 3993450 | N8: =EDATE(I8,K8) -> 45202 | O8: =AVERAGEIFS(Vendor_Analysis!G:G,Vendor_Analysis!B:B,Scenario_Modelling!A8) -> 54.5 | P8: =N8+O8 -> 45256.5 | Q8: =P8 -> 45256.5 | R8: =L8 -> -542667 | S8: =E8-G8 -> -723556 | T8: =S8/E8 -> -0.18978214 | U8: =M8-E8 -> 180889 | V8: =U8/E8 -> 0.047445536 | W8: =M8-G8 -> -542667 | X8: =W8/G8 -> -0.1196325
A9: PRJ0007 | B9: =Capex_Budgets!B8 -> Platform - PRJ0007 | C9: =Capex_Budgets!G8 -> ProprietaryHardware | D9: =Capex_Budgets!C8 -> DPT003 | E9: =Capex_Budgets!D8 -> 3308526 | F9: =INDEX(Capex_Budgets!E:E,MATCH(Scenario_Modelling!A9,Capex_Budgets!A:A)) -> 45236 | G9: =SUMIF(Capex_Actuals!B:B,Scenario_Modelling!A9,Capex_Actuals!E:E) -> 2983438 | H9: =E9-G9 -> 325088 | I9: {=MIN(IF(Capex_Actuals!B:B=Scenario_Modelling!A9,Capex_Actuals!D:D))} -> 45237 | J9: 0.25 | K9: 2 | L9: =IF(H9>=0, H9*(1+J9), H9*(1-J9)) -> 406360 | M9: =G9+L9 -> 3389798 | N9: =EDATE(I9,K9) -> 45298 | O9: =AVERAGEIFS(Vendor_Analysis!G:G,Vendor_Analysis!B:B,Scenario_Modelling!A9) -> 52.788462 | P9: =N9+O9 -> 45350.788 | Q9: =P9 -> 45350.788 | R9: =L9 -> 406360 | S9: =E9-G9 -> 325088 | T9: =S9/E9 -> 0.098257653 | U9: =M9-E9 -> 81272 | V9: =U9/E9 -> 0.024564413 | W9: =M9-G9 -> 406360 | X9: =W9/G9 -> 0.13620528
A10: PRJ0008 | B10: =Capex_Budgets!B9 -> Platform - PRJ0008 | C10: =Capex_Budgets!G9 -> Hardware | D10: =Capex_Budgets!C9 -> DPT001 | E10: =Capex_Budgets!D9 -> 8079602 | F10: =INDEX(Capex_Budgets!E:E,MATCH(Scenario_Modelling!A10,Capex_Budgets!A:A)) -> 45139 | G10: =SUMIF(Capex_Actuals!B:B,Scenario_Modelling!A10,Capex_Actuals!E:E) -> 8818141 | H10: =E10-G10 -> -738539 | I10: {=MIN(IF(Capex_Actuals!B:B=Scenario_Modelling!A10,Capex_Actuals!D:D))} -> 45141 | J10: 0.25 | K10: 2 | L10: =IF(H10>=0, H10*(1+J10), H10*(1-J10)) -> -553904.25 | M10: =G10+L10 -> 8264236.8 | N10: =EDATE(I10,K10) -> 45202 | O10: =AVERAGEIFS(Vendor_Analysis!G:G,Vendor_Analysis!B:B,Scenario_Modelling!A10) -> 61.5 | P10: =N10+O10 -> 45263.5 | Q10: =P10 -> 45263.5 | R10: =L10 -> -553904.25 | S10: =E10-G10 -> -738539 | T10: =S10/E10 -> -0.091407844 | U10: =M10-E10 -> 184634.75 | V10: =U10/E10 -> 0.022851961 | W10: =M10-G10 -> -553904.25 | X10: =W10/G10 -> -0.062814175
A11: PRJ0009 | B11: =Capex_Budgets!B10 -> R&D - PRJ0009 | C11: =Capex_Budgets!G10 -> Compute | D11: =Capex_Budgets!C10 -> DPT005 | E11: =Capex_Budgets!D10 -> 7006978 | F11: =INDEX(Capex_Budgets!E:E,MATCH(Scenario_Modelling!A11,Capex_Budgets!A:A)) -> 45462 | G11: =SUMIF(Capex_Actuals!B:B,Scenario_Modelling!A11,Capex_Actuals!E:E) -> 7061476 | H11: =E11-G11 -> -54498 | I11: {=MIN(IF(Capex_Actuals!B:B=Scenario_Modelling!A11,Capex_Actuals!D:D))} -> 45464 | J11: 0.25 | K11: 2 | L11: =IF(H11>=0, H11*(1+J11), H11*(1-J11)) -> -40873.5 | M11: =G11+L11 -> 7020602.5 | N11: =EDATE(I11,K11) -> 45525 | O11: =AVERAGEIFS(Vendor_Analysis!G:G,Vendor_Analysis!B:B,Scenario_Modelling!A11) -> 50.25 | P11: =N11+O11 -> 45575.25 | Q11: =P11 -> 45575.25 | R11: =L11 -> -40873.5 | S11: =E11-G11 -> -54498 | T11: =S11/E11 -> -0.0077776753 | U11: =M11-E11 -> 13624.5 | V11: =U11/E11 -> 0.0019444188 | W11: =M11-G11 -> -40873.5 | X11: =W11/G11 -> -0.0057882375
A12: PRJ0010 | B12: =Capex_Budgets!B11 -> Platform - PRJ0010 | C12: =Capex_Budgets!G11 -> Compute | D12: =Capex_Budgets!C11 -> DPT003 | E12: =Capex_Budgets!D11 -> 7629267 | F12: =INDEX(Capex_Budgets!E:E,MATCH(Scenario_Modelling!A12,Capex_Budgets!A:A)) -> 45355 | G12: =SUMIF(Capex_Actuals!B:B,Scenario_Modelling!A12,Capex_Actuals!E:E) -> 8164037 | H12: =E12-G12 -> -534770 | I12: {=MIN(IF(Capex_Actuals!B:B=Scenario_Modelling!A12,Capex_Actuals!D:D))} -> 45374 | J12: 0.25 | K12: 2 | L12: =IF(H12>=0, H12*(1+J12), H12*(1-J12)) -> -401077.5 | M12: =G12+L12 -> 7762959.5 | N12: =EDATE(I12,K12) -> 45435 | O12: =AVERAGEIFS(Vendor_Analysis!G:G,Vendor_Analysis!B:B,Scenario_Modelling!A12) -> 56.590909 | P12: =N12+O12 -> 45491.591 | Q12: =P12 -> 45491.591 | R12: =L12 -> -401077.5 | S12: =E12-G12 -> -534770 | T12: =S12/E12 -> -0.070094545 | U12: =M12-E12 -> 133692.5 | V12: =U12/E12 -> 0.017523636 | W12: =M12-G12 -> -401077.5 | X12: =W12/G12 -> -0.04912735
A13: PRJ0011 | B13: =Capex_Budgets!B12 -> Hybrid Clients - PRJ0011 | C13: =Capex_Budgets!G12 -> R&D | D13: =Capex_Budgets!C12 -> DPT003 | E13: =Capex_Budgets!D12 -> 2712927 | F13: =INDEX(Capex_Budgets!E:E,MATCH(Scenario_Modelling!A13,Capex_Budgets!A:A)) -> 45139 | G13: =SUMIF(Capex_Actuals!B:B,Scenario_Modelling!A13,Capex_Actuals!E:E) -> 3478205 | H13: =E13-G13 -> -765278 | I13: {=MIN(IF(Capex_Actuals!B:B=Scenario_Modelling!A13,Capex_Actuals!D:D))} -> 45155 | J13: 0.25 | K13: 2 | L13: =IF(H13>=0, H13*(1+J13), H13*(1-J13)) -> -573958.5 | M13: =G13+L13 -> 2904246.5 | N13: =EDATE(I13,K13) -> 45216 | O13: =AVERAGEIFS(Vendor_Analysis!G:G,Vendor_Analysis!B:B,Scenario_Modelling!A13) -> 62.75 | P13: =N13+O13 -> 45278.75 | Q13: =P13 -> 45278.75 | R13: =L13 -> -573958.5 | S13: =E13-G13 -> -765278 | T13: =S13/E13 -> -0.28208573 | U13: =M13-E13 -> 191319.5 | V13: =U13/E13 -> 0.070521433 | W13: =M13-G13 -> -573958.5 | X13: =W13/G13 -> -0.16501572
A14: PRJ0012 | B14: =Capex_Budgets!B13 -> Platform - PRJ0012 | C14: =Capex_Budgets!G13 -> Hardware | D14: =Capex_Budgets!C13 -> DPT003 | E14: =Capex_Budgets!D13 -> 5466843 | F14: =INDEX(Capex_Budgets!E:E,MATCH(Scenario_Modelling!A14,Capex_Budgets!A:A)) -> 45274 | G14: =SUMIF(Capex_Actuals!B:B,Scenario_Modelling!A14,Capex_Actuals!E:E) -> 5899923 | H14: =E14-G14 -> -433080 | I14: {=MIN(IF(Capex_Actuals!B:B=Scenario_Modelling!A14,Capex_Actuals!D:D))} -> 45289 | J14: 0.25 | K14: 2 | L14: =IF(H14>=0, H14*(1+J14), H14*(1-J14)) -> -324810 | M14: =G14+L14 -> 5575113 | N14: =EDATE(I14,K14) -> 45351 | O14: =AVERAGEIFS(Vendor_Analysis!G:G,Vendor_Analysis!B:B,Scenario_Modelling!A14) -> 47.222222 | P14: =N14+O14 -> 45398.222 | Q14: =P14 -> 45398.222 | R14: =L14 -> -324810 | S14: =E14-G14 -> -433080 | T14: =S14/E14 -> -0.079219396 | U14: =M14-E14 -> 108270 | V14: =U14/E14 -> 0.019804849 | W14: =M14-G14 -> -324810 | X14: =W14/G14 -> -0.055053261
... A47: PRJ0045 | B47: =Capex_Budgets!B46 -> Hybrid Clients - PRJ0045 | C47: =Capex_Budgets!G46 -> Storage | D47: =Capex_Budgets!C46 -> DPT005 | E47: =Capex_Budgets!D46 -> 501071 | F47: =INDEX(Capex_Budgets!E:E,MATCH(Scenario_Modelling!A47,Capex_Budgets!A:A)) -> 45185 | G47: =SUMIF(Capex_Actuals!B:B,Scenario_Modelling!A47,Capex_Actuals!E:E) -> 560878 | H47: =E47-G47 -> -59807 | I47: {=MIN(IF(Capex_Actuals!B:B=Scenario_Modelling!A47,Capex_Actuals!D:D))} -> 45203 | J47: 0.25 | K47: 2 | L47: =IF(H47>=0, H47*(1+J47), H47*(1-J47)) -> -44855.25 | M47: =G47+L47 -> 516022.75 | N47: =EDATE(I47,K47) -> 45264 | O47: =AVERAGEIFS(Vendor_Analysis!G:G,Vendor_Analysis!B:B,Scenario_Modelling!A47) -> 56.4 | P47: =N47+O47 -> 45320.4 | Q47: =P47 -> 45320.4 | R47: =L47 -> -44855.25 | S47: =E47-G47 -> -59807 | T47: =S47/E47 -> -0.11935833 | U47: =M47-E47 -> 14951.75 | V47: =U47/E47 -> 0.029839584 | W47: =M47-G47 -> -44855.25 | X47: =W47/G47 -> -0.079973274

Sheet Sheet4
H3: Row Labels | I3: Sum of Amount_Spent
H4: PRJ0026 | I4: 5355988
H5: Jan | I5: 316686
H6: Feb | I6: 689475
H7: Mar | I7: 422599
H8: Apr | I8: 929093
H9: May | I9: 249299
H10: Jun | I10: 595062
H11: Jul | I11: 159424
H12: Aug | I12: 592147
H13: Sep | I13: 1402203
H14: Grand Total | I14: 5355988

Sheet Capex_Actuals
A1: Transaction_ID | B1: Project_ID | C1: Vendor | D1: Transaction_Date | E1: Amount_Spent
A2: TX0001-001 | B2: PRJ0001 | C2: VEND0017 | D2: 45179 | E2: 38577
A3: TX0001-002 | B3: PRJ0001 | C3: VEND0024 | D3: 45181 | E3: 79555
A4: TX0001-003 | B4: PRJ0001 | C4: VEND0006 | D4: 45184 | E4: 73361
A5: TX0001-004 | B5: PRJ0001 | C5: VEND0016 | D5: 45191 | E5: 55178
A6: TX0001-005 | B6: PRJ0001 | C6: VEND0009 | D6: 45197 | E6: 97145
A7: TX0001-006 | B7: PRJ0001 | C7: VEND0006 | D7: 45201 | E7: 97663
A8: TX0001-007 | B8: PRJ0001 | C8: VEND0015 | D8: 45208 | E8: 50793
A9: TX0001-008 | B9: PRJ0001 | C9: VEND0012 | D9: 45209 | E9: 84554
A10: TX0001-009 | B10: PRJ0001 | C10: VEND0025 | D10: 45213 | E10: 60509
A11: TX0001-010 | B11: PRJ0001 | C11: VEND0020 | D11: 45222 | E11: 82632
A12: TX0001-011 | B12: PRJ0001 | C12: VEND0009 | D12: 45241 | E12: 73839
A13: TX0001-012 | B13: PRJ0001 | C13: VEND0010 | D13: 45245 | E13: 161273
... A1935: TX0045-050 | B1935: PRJ0045 | C1935: VEND0008 | D1935: 45760 | E1935: 8961

Sheet Capex_Budgets
A1: Project_ID | B1: Project_Name | C1: Department | D1: Approved_Budget | E1: Start_Date | F1: End_Date | G1: Capex_Category
A2: PRJ0001 | B2: Infra - PRJ0001 | C2: DPT001 | D2: 5543627 | E2: 45139 | F2: 45900 | G2: Storage
A3: PRJ0002 | B3: Infra - PRJ0002 | C3: DPT004 | D3: 6018833 | E3: 45372 | F3: 45586 | G3: ProprietaryHardware
A4: PRJ0003 | B4: R&D - PRJ0003 | C4: DPT001 | D4: 6171576 | E4: 45190 | F4: 45586 | G4: Compute
A5: PRJ0004 | B5: R&D - PRJ0004 | C5: DPT003 | D5: 444469 | E5: 45232 | F5: 45840 | G5: DataCenter
A6: PRJ0005 | B6: Infra - PRJ0005 | C6: DPT001 | D6: 8956949 | E6: 45192 | F6: 45711 | G6: ProprietaryHardware
A7: PRJ0006 | B7: Platform - PRJ0006 | C7: DPT002 | D7: 3812561 | E7: 45139 | F7: 45900 | G7: ProprietaryHardware
A8: PRJ0007 | B8: Platform - PRJ0007 | C8: DPT003 | D8: 3308526 | E8: 45236 | F8: 45844 | G8: ProprietaryHardware
A9: PRJ0008 | B9: Platform - PRJ0008 | C9: DPT001 | D9: 8079602 | E9: 45139 | F9: 45900 | G9: Hardware
A10: PRJ0009 | B10: R&D - PRJ0009 | C10: DPT005 | D10: 7006978 | E10: 45462 | F10: 45676 | G10: Compute
A11: PRJ0010 | B11: Platform - PRJ0010 | C11: DPT003 | D11: 7629267 | E11: 45355 | F11: 45600 | G11: Compute
A12: PRJ0011 | B12: Hybrid Clients - PRJ0011 | C12: DPT003 | D12: 2712927 | E12: 45139 | F12: 45900 | G12: R&D
A13: PRJ0012 | B13: Platform - PRJ0012 | C13: DPT003 | D13: 5466843 | E13: 45274 | F13: 45579 | G13: Hardware
... A46: PRJ0045 | B46: Hybrid Clients - PRJ0045 | C46: DPT005 | D46: 501071 | E46: 45185 | F46: 45763 | G46: Storage
A47: PRJ0001 | B47: Infra - PRJ0001 | C47: DPT001 | D47: 800000

Sheet Capex_Forecast
A1: Project_ID | B1: Month | C1: Forecasted_Spend | D1: Updated_By | E1: Forecast_Date
A2: PRJ0001 | B2: 2023-08 | C2: 107996 | D2: Ian Oneill | E2: 45419
A3: PRJ0001 | B3: 2023-09 | C3: 185488 | D3: Matthew Holmes | E3: 45490
A4: PRJ0001 | B4: 2023-10 | C4: 221419 | D4: Amy Fisher | E4: 45602
A5: PRJ0001 | B5: 2023-11 | C5: 130468 | D5: Michael Thomas | E5: 45280
A6: PRJ0001 | B6: 2023-12 | C6: 189430 | D6: Matthew Holmes | E6: 45755
A7: PRJ0001 | B7: 2024-01 | C7: 146990 | D7: Amy Fisher | E7: 45857
A8: PRJ0001 | B8: 2024-02 | C8: 140863 | D8: Nicole Carpenter | E8: 45867
A9: PRJ0001 | B9: 2024-03 | C9: 132099 | D9: Ian Oneill | E9: 45344
A10: PRJ0001 | B10: 2024-04 | C10: 158077 | D10: Ian Oneill | E10: 45778
A11: PRJ0001 | B11: 2024-05 | C11: 156561 | D11: Amy Fisher | E11: 45842
A12: PRJ0001 | B12: 2024-06 | C12: 192205 | D12: Nicole Carpenter | E12: 45827
A13: PRJ0001 | B13: 2024-07 | C13: 103349 | D13: Michael Thomas | E13: 45866
... A790: PRJ0045 | B790: 2025-04 | C790: 21260 | D790: Matthew Holmes | E790: 45883

Sheet Departments
A1: Department_ID | B1: Department_Name | C1: Cost_Center
A2: DPT001 | B2: Cloud Operations & Infrastructure | C2: CC-1001
A3: DPT002 | B3: Sales & Business Development | C3: CC-1002
A4: DPT003 | B4: Engineering & Product Development | C4: CC-1003
A5: DPT004 | B5: Marketing & Communications | C5: CC-1004
A6: DPT005 | B6: Customer Success & Support | C6: CC-1005
A7: DPT006 | B7: Finance, HR & Administration | C7: CC-1006

Sheet Project_Master
A1: Project_ID | B1: Project_Manager | C1: Region | D1: Business_Unit | E1: ROI_Expected | F1: ROI_Realized | G1: Start_Date | H1: End_Date | I1: Department_ID
A2: PRJ0001 | B2: Brian Rice | C2: EMEA | D2: Infra | E2: 0.319 | F2: 0.194 | G2: 45139 | H2: 45900 | I2: DPT001
A3: PRJ0002 | B3: Henry Jackson | C3: APAC | D3: Infra | E3: 0.114 | F3: 0.109 | G3: 45372 | H3: 45586 | I3: DPT004
A4: PRJ0003 | B4: Kelsey Anderson | C4: LATAM | D4: R&D | E4: 0.05 | F4: 0.06 | G4: 45190 | H4: 45586 | I4: DPT001
A5: PRJ0004 | B5: Philip Mcknight | C5: EMEA | D5: R&D | E5: 0.244 | F5: 0.172 | G5: 45232 | H5: 45840 | I5: DPT003
A6: PRJ0005 | B6: Justin Oliver | C6: APAC | D6: Infra | E6: 0.091 | F6: 0.085 | G6: 45192 | H6: 45711 | I6: DPT001
A7: PRJ0006 | B7: Lori Wilkins | C7: EMEA | D7: Platform | E7: 0.437 | F7: 0.427 | G7: 45139 | H7: 45900 | I7: DPT002
A8: PRJ0007 | B8: Vincent Johnson | C8: APAC | D8: Platform | E8: 0.303 | F8: 0.233 | G8: 45236 | H8: 45844 | I8: DPT003
A9: PRJ0008 | B9: Teresa Nelson | C9: NA | D9: Platform | E9: 0.105 | F9: 0.089 | G9: 45139 | H9: 45900 | I9: DPT001
A10: PRJ0009 | B10: Daniel Daniels | C10: LATAM | D10: R&D | E10: 0.39 | F10: 0.311 | G10: 45462 | H10: 45676 | I10: DPT005
A11: PRJ0010 | B11: Johnathan Morris | C11: APAC | D11: Platform | E11: 0.486 | F11: 0.507 | G11: 45355 | H11: 45600 | I11: DPT003
A12: PRJ0011 | B12: Tom Rivera | C12: LATAM | D12: Hybrid Clients | E12: 0.465 | F12: 0.261 | G12: 45139 | H12: 45900 | I12: DPT003
A13: PRJ0012 | B13: Ronald Ross | C13: EMEA | D13: Platform | E13: 0.386 | F13: 0.339 | G13: 45274 | H13: 45579 | I13: DPT003
... A46: PRJ0045 | B46: Lisa Brown | C46: APAC | D46: Hybrid Clients | E46: 0.439 | F46: 0.29 | G46: 45185 | H46: 45763 | I46: DPT005

Sheet Vendors
A1: Vendor_ID | B1: Vendor_Name | C1: Category | D1: Payment_Terms | E1: Pay_Terms
A2: VEND0001 | B2: Hancock and Sons | C2: Consulting | D2: 30 days | E2: =SUBSTITUTE(D2,"days","") -> 30
A3: VEND0002 | B3: Conner, Lloyd and Green | C3: Hardware | D3: 60 days | E3: =SUBSTITUTE(D3,"days","") -> 60
A4: VEND0003 | B4: Wilson-Mayer | C4: Services | D4: 45 days | E4: =SUBSTITUTE(D4,"days","") -> 45
A5: VEND0004 | B5: Johnson, Kirk and Ruiz | C5: Services | D5: 30 days | E5: =SUBSTITUTE(D5,"days","") -> 30
A6: VEND0005 | B6: Roberts LLC | C6: Consulting | D6: 30 days | E6: =SUBSTITUTE(D6,"days","") -> 30
A7: VEND0006 | B7: Harris-Campbell | C7: Cloud | D7: Net 90 | E7: =SUBSTITUTE(D7,"Net","") -> 90
A8: VEND0007 | B8: Fox PLC | C8: Hardware | D8: 30 days | E8: =SUBSTITUTE(D8,"days","") -> 30
A9: VEND0008 | B9: Brooks, Owens and Martinez | C9: Hardware | D9: 45 days | E9: =SUBSTITUTE(D9,"days","") -> 45
A10: VEND0009 | B10: Hill, Chandler and Evans | C10: Services | D10: 30 days | E10: =SUBSTITUTE(D10,"days","") -> 30
A11: VEND0010 | B11: Rush, Rogers and Burns | C11: Cloud | D11: 45 days | E11: =SUBSTITUTE(D11,"days","") -> 45
A12: VEND0011 | B12: Brandt-Jarvis | C12: Consulting | D12: Net 90 | E12: =SUBSTITUTE(D12,"Net","") -> 90
A13: VEND0012 | B13: Ross LLC | C13: Services | D13: Net 90 | E13: =SUBSTITUTE(D13,"Net","") -> 90
A14: VEND0013 | B14: Norman-Powers | C14: Cloud | D14: 60 days | E14: =SUBSTITUTE(D14,"days","") -> 60
A15: VEND0014 | B15: Robinson Group | C15: Hardware | D15: 45 days | E15: =SUBSTITUTE(D15,"days","") -> 45
A16: VEND0015 | B16: Sloan-Deleon | C16: Consulting | D16: Net 90 | E16: =SUBSTITUTE(D16,"Net","") -> 90
A17: VEND0016 | B17: Jackson Inc | C17: Networking | D17: 60 days | E17: =SUBSTITUTE(D17,"days","") -> 60
A18: VEND0017 | B18: Hughes Ltd | C18: Services | D18: 45 days | E18: =SUBSTITUTE(D18,"days","") -> 45
A19: VEND0018 | B19: White-Gould | C19: Networking | D19: 30 days | E19: =SUBSTITUTE(D19,"days","") -> 30
A20: VEND0019 | B20: Phillips, Forbes and Keller | C20: Hardware | D20: Net 90 | E20: =SUBSTITUTE(D20,"Net","") -> 90
A21: VEND0020 | B21: Mcintyre and Sons | C21: Hardware | D21: 60 days | E21: =SUBSTITUTE(D21,"days","") -> 60
A22: VEND0021 | B22: Frank and Sons | C22: Networking | D22: 60 days | E22: =SUBSTITUTE(D22,"days","") -> 60
A23: VEND0022 | B23: Brown, Kirby and Holmes | C23: Hardware | D23: Net 90 | E23: =SUBSTITUTE(D23,"Net","") -> 90
A24: VEND0023 | B24: Burton, Boyd and Mcbride | C24: Cloud | D24: 30 days | E24: =SUBSTITUTE(D24,"days","") -> 30
A25: VEND0024 | B25: Herrera-Myers | C25: Construction | D25: 30 days | E25: =SUBSTITUTE(D25,"days","") -> 30
A26: VEND0025 | B26: Jackson Ltd | C26: Cloud | D26: 60 days | E26: =SUBSTITUTE(D26,"days","") -> 60
